plugins4all/__init__.py
plugins4all/plugins4all.py
plugins4all-1.0.1.dist-info/LICENSE.txt
plugins4all-1.0.1.dist-info/METADATA
plugins4all-1.0.1.dist-info/WHEEL
plugins4all-1.0.1.dist-info/top_level.txt
plugins4all-1.0.1.dist-info/RECORD
