Metadata-Version: 2.1
Name: plugins4all
Version: 1.0.1
Summary: Bringing ChatGPT plugins to all local LLMs.
Home-page: https://github.com/Icemaster-Eric/plugins4all
Author: Eric Li
Author-email: icemastereric@gmail.com
Project-URL: Bug Tracker, https://github.com/Icemaster-Eric/plugins4all/issues
Project-URL: repository, https://github.com/Icemaster-Eric/plugins4all
Classifier: Programming Language :: Python :: 3
Classifier: License :: OSI Approved :: MIT License
Classifier: Operating System :: OS Independent
Requires-Python: >=3.8
License-File: LICENSE.txt
